<entry-oprwy>
    <id>70</id>
    <filename>runway.bin</filename>
    <data>
        <runways>
            <str-tunarray-element str-tunarray-key="0">
                <runway>
                    <loides>
                        <ref-kval>
                            <type>65534</type>
                            <kval>
                                <wrt-choice>
                                    <wrt-choice-abs>
                                        <wrt>65535</wrt>
                                        <pos>
                                            <x>501256256</x>
                                            <y>-4970413</y>
                                            <z>393076430</z>
                                        </pos>
                                    </wrt-choice-abs>
                                </wrt-choice>
                            </kval>
                        </ref-kval>
                    </loides>
                    <alarms_cfg/>
                    <fstart>
                        <ref-kval>
                            <type>65534</type>
                            <kval>
                                <wrt-choice>
                                    <wrt-choice-abs>
                                        <wrt>65535</wrt>
                                        <pos>
                                            <x>501275198</x>
                                            <y>-5026926</y>
                                            <z>393033967</z>
                                        </pos>
                                    </wrt-choice-abs>
                                </wrt-choice>
                            </kval>
                        </ref-kval>
                    </fstart>
                    <fend>
                        <ref-kval>
                            <type>65534</type>
                            <kval>
                                <wrt-choice>
                                    <wrt-choice-abs>
                                        <wrt>65535</wrt>
                                        <pos>
                                            <x>501290419</x>
                                            <y>-4890955</y>
                                            <z>393012996</z>
                                        </pos>
                                    </wrt-choice-abs>
                                </wrt-choice>
                            </kval>
                        </ref-kval>
                    </fend>
                    <preferred>0</preferred>
                    <margin-ratio>0.4</margin-ratio>
                    <margin-reverse-ratio>0.6</margin-reverse-ratio>
                </runway>
            </str-tunarray-element>
        </runways>
        <spots/>
    </data>
</entry-oprwy>
